weather/__init__.py
weather/weather.py
freeweather-0.1.1.dist-info/LICENSE
freeweather-0.1.1.dist-info/METADATA
freeweather-0.1.1.dist-info/WHEEL
freeweather-0.1.1.dist-info/top_level.txt
freeweather-0.1.1.dist-info/RECORD
